koball
